alertscraper/__init__.py
alertscraper/alertscraper.py
alertscraper-0.1.7.dist-info/DESCRIPTION.rst
alertscraper-0.1.7.dist-info/METADATA
alertscraper-0.1.7.dist-info/RECORD
alertscraper-0.1.7.dist-info/WHEEL
alertscraper-0.1.7.dist-info/entry_points.txt
alertscraper-0.1.7.dist-info/metadata.json
alertscraper-0.1.7.dist-info/top_level.txt
